njson/__init__.py
njson/njson.py
njson-1.2.0.dist-info/LICENSE
njson-1.2.0.dist-info/METADATA
njson-1.2.0.dist-info/WHEEL
njson-1.2.0.dist-info/RECORD
