Metadata-Version: 2.1
Name: njson
Version: 1.2.0
Summary: Provide fast JSON-like data transformation to and from nested parent-child and flat label-value data items, such as Pandas `Series` with MultiIndex index.
Home-page: https://gitlab.com/martins-bruvelis/njson
Author: Martins Bruvelis
Author-email: martins.bruvelis@gmail.com
Requires-Python: >=3.7,<4.0
Classifier: Programming Language :: Python :: 3
Classifier: Programming Language :: Python :: 3.7
Classifier: Programming Language :: Python :: 3.8
Classifier: Programming Language :: Python :: 3.9
Classifier: Programming Language :: Python :: 3.10
Classifier: Programming Language :: Python :: 3.11
Classifier: Programming Language :: Python :: 3.12
Project-URL: Documentation, https://gitlab.com/martins-bruvelis/njson/-/blob/main/README.md
Project-URL: Repository, https://gitlab.com/martins-bruvelis/njson
